cli/__init__.py
cli/superbuddy.py
superbuddy-0.0.5.dist-info/METADATA
superbuddy-0.0.5.dist-info/WHEEL
superbuddy-0.0.5.dist-info/entry_points.txt
superbuddy-0.0.5.dist-info/top_level.txt
superbuddy-0.0.5.dist-info/RECORD
