Metadata-Version: 2.1
Name: superbuddy
Version: 0.0.5
Summary: UNKNOWN
Home-page: UNKNOWN
Author: Rahul Shome
Author-email: rahulshome8@gmail.com
License: UNKNOWN
Keywords: example
Platform: UNKNOWN
Requires-Dist: click
